unidock_tools/__init__.py
unidock_tools/unidock.py
unidock_tools/ligandPrepare/__init__.py
unidock_tools/ligandPrepare/atom_type.py
unidock_tools/ligandPrepare/rotatable_bond.py
unidock_tools/ligandPrepare/topology_builder.py
unidock_tools/ligandPrepare/utils.py
unidock_tools-1.1.2.dist-info/LICENSE
unidock_tools-1.1.2.dist-info/METADATA
unidock_tools-1.1.2.dist-info/WHEEL
unidock_tools-1.1.2.dist-info/entry_points.txt
unidock_tools-1.1.2.dist-info/top_level.txt
unidock_tools-1.1.2.dist-info/RECORD
