Metadata-Version: 2.1
Name: unidock-tools
Version: 1.1.2
Summary: A data processing tool for Uni-Dock input and output
Home-page: https://github.com/UR-Free/unidock_tools
Author: DP Technology
Author-email: yanghe@dp.tech
License: UNKNOWN
Platform: UNKNOWN
License-File: LICENSE
Requires-Dist: rdkit
Requires-Dist: networkx
Requires-Dist: numpy
